MANIFEST.in
README.rst
setup.cfg
setup.py
notebooks/Example.ipynb
notebooks/.ipynb_checkpoints/Example-checkpoint.ipynb
pyMPM/MPM.py
pyMPM/__init__.py
pyMPM/oxygen93.txt
pyMPM/water93.txt
pyMPM.egg-info/PKG-INFO
pyMPM.egg-info/SOURCES.txt
pyMPM.egg-info/dependency_links.txt
pyMPM.egg-info/requires.txt
pyMPM.egg-info/top_level.txt