Metadata-Version: 1.1
Name: pyMPM
Version: 0.0.2
Summary: Python version of the MPM millimeter wave propagation model
Home-page: http://github.com/cchwala/pyMPM
Author: Christian Chwala
Author-email: christian.chwala@kit.edu
License: BSD
Keywords: microwave propagation atmosphere
Platform: UNKNOWN
Classifier: Development Status :: 3 - Alpha
Classifier: Topic :: Scientific/Engineering :: Atmospheric Science
Classifier: License :: OSI Approved :: BSD License
Classifier: Programming Language :: Python :: 2.7
